{
	"info": {
		"_postman_id": "9e5bfa62-540d-4fc0-8612-c5d39ed38ec0",
		"name": "SanctionScanner.WebApi",
		"schema": "https://schema.getpostman.com/json/collection/v2.1.0/collection.json",
		"_exporter_id": "25458337"
	},
	"item": [
		{
			"name": "GetBooks",
			"request": {
				"method": "GET",
				"header": [],
				"url": {
					"raw": "{{baseuUrl}}/api/Home/GetBooks?page=1&size=10\n",
					"host": [
						"{{baseuUrl}}"
					],
					"path": [
						"api",
						"Home",
						"GetBooks"
					],
					"query": [
						{
							"key": "page",
							"value": "1"
						},
						{
							"key": "size",
							"value": "10\n"
						}
					]
				}
			},
			"response": []
		}
	]
}